{
 "title": "Notas da Atualização 10.10",
 "note": "Mais uma atualização! Quem diria, hein?! Hoje, na passarela dos Campeões que estão sofrendo já faz um tempinho, apresentamos: Udyr, Nidalee e Sivir! Vamos tentar melhorar a situação deles, prometemos! Também ajustaremos alguns dos personagens mais fortes que estão passando dos limites quando o assunto é balanceamento. Dica: eles gostam de árvores, adagas e gemas (pura emoção!). Ah, e o URF está de volta! Não percam a chance de jogar partidas mais ultrarrápidas e furiosas do que nunca! Pule neste portal se você está procurando pelas Notas de Atualização do TFT!",
 "ft": {
  "img": "Patch_10.10_Infographic_1080x1080_v3_ptBR.jpg",
  "mod": "Pantheon, Lucian (+ Edição de Prestígio), Fiora e Ekko Pulsefire estarão disponíveis no dia 14 de maio de 2020.\n\t\t\t\t\n\t\t\t\n\t\n\n\t\n\t\tComportamento dos jogadores\n\t\n\t\n\t\t\n\t\t\t\n\t\t\t\t\n\t\t\t\t\tNa semana passada, conversamos com vocês sobre nossos planos (de curto e longo prazo) para lidar com os comportamentos nocivos para as partidas. Nossos planos não foram feitos para atingir as pessoas que estão apenas tendo uma partida ruim, mas aquelas que decidiram sozinhas que a partida já acabou e ficam trolando as demais em vez de se esforçarem para vencer. A primeira iniciativa a curto prazo é ajustar nosso sistema de Denúncia e Punição já na 10.10. Com isso, vocês receberão a notificação de \"Feedback Instantâneo\" por comportamento inadequado com mais frequência conforme ajustamos nossos sistemas comportamentais.  Para saber mais, basta acessar o artigo.\n\t\t\t\t\n\t\t\t\n\t\t\n\t\n\n\t\n\t\tCampeões\n\t\n\t\n\t\t\n\t\t\t\n\t\t\t\t\n\t\t\t\tAnnie\n\t\t\t\tRedução de dano do E aumentada e aura de queima do Tibbers fortalecida.\n\t\t\t\t\n\t\t\t\t\tFortaleceremos o Tibbers para encorajar quem joga de Annie a brincar mais com ele (e nunca com fósforos). Também aumentaremos a redução de dano do Escudo Fundido, já que a habilidade estava um pouco fraca desde sua pequena atualização na 9.18.\n\t\t\t\t\n\t\t\t\t\n\t\t\t\tE - Escudo Fundido\n\t\t\t\t\n\t\t\t\t\tREDUÇÃO DE DANO 10/13/16/19/22% ⇒ 13/17/21/25/29%\n\t\t\t\t\n\t\t\t\t\n\t\t\t\tR - Invocar: Tibbers\n\t\t\t\t\n\t\t\t\t\tDANO DA AURA DO TIBBERS 10/15/20 (+0,1 de Poder de Habilidade) ⇒ 20/30/40 (+0,12 de Poder de Habilidade)\n\t\t\t\t\n\t\t\t\n\t\t\n\t\n\t\n\t\t\n\t\t\t\n\t\t\t\t\n\t\t\t\tDiana\n\t\t\t\tVida base e Dano de Ataque reduzidos.\n\t\t\t\t\n\t\t\t\t\tDiana está se mostrando o terror das partidas de alto e médio nível de habilidade e, Apesar de sua agressividade na rota ser algo planejado, achamos que ela não está pagando o preço certo por se colocar em risco.\n\t\t\t\t\n\t\t\t\t\n\t\t\t\tAtributos base\n\t\t\t\t\n\t\t\t\t\tVIDA 594 ⇒ 570\n\t\t\t\t\n\t\t\t\t\n\t\t\t\t\tDANO DE ATAQUE 57,04 ⇒ 57\n\t\t\t\t\n\t\t\t\n\t\t\n\t\n\t\n\t\t\n\t\t\t\n\t\t\t\t\n\t\t\t\tIrelia\n\t\t\t\tDano base do E aumentado.\n\t\t\t\t\n\t\t\t\t\tIrelia permaneceu enfraquecida em todos os níveis de jogo por conta do cenário profissional, mas finalmente deixou de dominar as escolhas. Isso pede um empurrãozinho na direção certa.\n\t\t\t\t\n\t\t\t\t\n\t\t\t\tE - Dueto Impecável\n\t\t\t\t\n\t\t\t\t\tDANO BASE 70/110/150/190/230 ⇒ 80/125/170/215/260\n\t\t\t\t\n\t\t\t\n\t\t\n\t\n\t\n\t\t\n\t\t\t\n\t\t\t\t\n\t\t\t\tKatarina\n\t\t\t\tMultiplicador de PdH das adagas da Passiva reduzido.\n\t\t\t\t\n\t\t\t\t\tPor outro lado, essa outra fanática por lâminas anda aparecendo consistentemente no limite do balanceamento e, portanto, reduziremos os multiplicadores de PdH. Adagas mais afiadas serão necessárias se ela quiser continuar explodindo os inimigos por aí.\n\t\t\t\t\n\t\t\t\t\n\t\t\t\tPassiva - Voracidade\n\t\t\t\t\n\t\t\t\t\tMULTIPLICADOR DE DANO DA ADAGA 0,55/0,70/0,85/1,0 de Poder de Habilidade ⇒ 0,55/0,66/0,77/0,88 de Poder de Habilidade\n\t\t\t\t\n\t\t\t\n\t\t\n\t\n\t\n\t\t\n\t\t\t\n\t\t\t\t\n\t\t\t\tKayn\n\t\t\t\tCura da Passiva do Rhaast reduzida.\n\t\t\t\t\n\t\t\t\t\tEmbora o Assassino das Sombras pareça estar no lugar certo, o Darkin anda atravessando demais os ̶i̶n̶i̶m̶i̶g̶o̶s̶ limites. Isso pede um enfraquecimento específico na utilidade da forma.\n\t\t\t\t\n\t\t\t\t\n\t\t\t\tPassiva - A Foice Darkin\n\t\t\t\t\n\t\t\t\t\tCURA DO RHAAST 34,5% - 43% do dano causado (níveis 1 a 18) ⇒ 30% - 40% do dano causado (níveis 1 a 18)\n\t\t\t\t\n\t\t\t\n\t\t\n\t\n\t\n\t\t\n\t\t\t\n\t\t\t\t\n\t\t\t\tKled\n\t\t\t\tTempo de Recarga do Q aumentado.\n\t\t\t\t\n\t\t\t\t\tAumentar o Tempo de Recarga significa que esse corajoso yordle e sua não-tão-corajosa montaria precisarão pensar duas vezes antes de tentar pescar alguém nos primeiros níveis.\n\t\t\t\t\n\t\t\t\t\n\t\t\t\tQ - Armadilha na Corda\n\t\t\t\t\n\t\t\t\t\tTEMPO DE RECARGA 9/8,5/8/7,5/7s ⇒ 11/10/9/8/7s\n\t\t\t\t\n\t\t\t\n\t\t\n\t\n\t\n\t\t\n\t\t\t\n\t\t\t\t\n\t\t\t\tMiss Fortune\n\t\t\t\tVelocidade de Movimento adicional máxima do W reduzida.\n\t\t\t\t\n\t\t\t\t\tFaremos essa pirata poderosa pisar menos... ̶L̶I̶T̶E̶R̶A̶L̶M̶E̶N̶T̶E̶!\n\t\t\t\t\n\t\t\t\t\n\t\t\t\tW - Desfilando\n\t\t\t\t\n\t\t\t\t\tVELOCIDADE DE MOVIMENTO ADICIONAL MÁXIMA 60/70/80/90/100 ⇒ 50/60/70/80/90\n\t\t\t\t\n\t\t\t\n\t\t\n\t\n\t\n\t\t\n\t\t\t\n\t\t\t\t\n\t\t\t\tMaokai\n\t\t\t\tMana base reduzida. Custo do Q aumentado.\n\t\t\t\t\n\t\t\t\t\tMaokai anda no topo da rota superior! Daremos a ele um pequeno enfraquecimento na esperança de cortar o mal pela raiz. (ba dum, tss)\n\t\t\t\t\n\t\t\t\t\n\t\t\t\tAtributos base\n\t\t\t\t\n\t\t\t\t\tMANA 377,28 ⇒ 375\n\t\t\t\t\n\t\t\t\t\n\t\t\t\tQ - Esmagamento Espinhoso\n\t\t\t\t\n\t\t\t\t\tCUSTO 50 de Mana ⇒ 60 de Mana\n\t\t\t\t\n\t\t\t\n\t\t\n\t\n\t\n\t\t\n\t\t\t\n\t\t\t\t\n\t\t\t\tNidalee\n\t\t\t\tMultiplicador de dano do Q aumentado.\n\t\t\t\t\n\t\t\t\t\tTentaremos colocar a Nida de volta na caçada fortalecendo sua habilidade mais famosa conforme ela escala para o fim de jogo.\n\t\t\t\t\n\t\t\t\t\n\t\t\t\tQ - Arremessar Lança\n\t\t\t\t\n\t\t\t\t\tMULTIPLICADOR DE DANO 0,4 de Poder de Habilidade (máximo de 1,2 de Poder de Habilidade) ⇒ 0,5 de Poder de Habilidade (máximo de 1,5 de Poder de Habilidade)\n\t\t\t\t\n\t\t\t\n\t\t\n\t\n\t\n\t\t\n\t\t\t\n\t\t\t\t\n\t\t\t\tSivir\n\t\t\t\tRestauração de Mana do E aumentada.\n\t\t\t\t\n\t\t\t\t\tFortaleceremos o restauração de Mana para encorajar os jogadores de Sivir a dominar a arte de mandar os inimigos \"pra trás\" ou elogiar uma \"bela tentativa\".\n\t\t\t\t\n\t\t\t\t\n\t\t\t\tE - Escudo de Feitiço\n\t\t\t\t\n\t\t\t\t\tRESTAURAÇÃO DE MANA 80/95/110/125/140 ⇒ 110/120/130/140/150\n\t\t\t\t\n\t\t\t\n\t\t\n\t\n\t\n\t\t\n\t\t\t\n\t\t\t\t\n\t\t\t\tSoraka\n\t\t\t\tDano base do Q aumentado. Redução do custo de Vida do W aumentado.\n\t\t\t\t\n\t\t\t\t\tSegundo nosso setor de astrologia, as próximas duas semanas serão mais complicadas para os inimigos da Sorakinha.\n\t\t\t\t\n\t\t\t\t\n\t\t\t\tQ - Chamado Estelar\n\t\t\t\t\n\t\t\t\t\tDANO BASE 75/110/145/180/215 ⇒ 85/120/155/190/225\n\t\t\t\t\n\t\t\t\t\n\t\t\t\tW - Infusão Astral\n\t\t\t\t\n\t\t\t\t\tREDUÇÃO DO CUSTO DE VIDA 60/70/80/90/100% ⇒ 80/85/90/95/100%\n\t\t\t\t\n\t\t\t\n\t\t\n\t\n\t\n\t\t\n\t\t\t\n\t\t\t\t\n\t\t\t\tTaric\n\t\t\t\tCrescimento de Vida base reduzido. Multiplicador de Armadura adicional do W reduzido nos últimos níveis.\n\t\t\t\t\n\t\t\t\t\tFaremos com que a sobrevivência de Taric dependa mais do uso de habilidades e reduziremos os atributos defensivos brutos dele e de seu aliado conectado.\n\t\t\t\t\n\t\t\t\t\n\t\t\t\tAtributos base\n\t\t\t\t\n\t\t\t\t\tCRESCIMENTO DE VIDA 90 ⇒ 85\n\t\t\t\t\n\t\t\t\t\n\t\t\t\tW - Bastião\n\t\t\t\t\n\t\t\t\t\tADICIONAL ARMADURA 10/12,5/15/17,5/20% da Armadura de Taric ⇒ 10/11/12/13/14% da Armadura de Taric\n\t\t\t\t\n\t\t\t\n\t\t\n\t\n\t\n\t\t\n\t\t\t\n\t\t\t\t\n\t\t\t\tTwisted Fate\n\t\t\t\tDano de Ataque base e Armadura aumentados. Custo de Mana do R reduzido.\n\t\t\t\t\n\t\t\t\t\tNosso TF anda sem sorte nas cartas e está bem sumido, apesar de ter conseguido escapar daquela bruxa do mar. Vamos ajudá-lo reduzindo um pouco o custo da ult, deixando-a mais alinhada com seus oponentes. Também daremos uma alavancada em seus atributos base para aumentar a capacidade de coleta e presença no início de jogo.\n\t\t\t\t\n\t\t\t\t\n\t\t\t\tAtributos base\n\t\t\t\t\n\t\t\t\t\tDANO DE ATAQUE 49,954 ⇒ 52\n\t\t\t\t\n\t\t\t\t\n\t\t\t\t\tARMADURA 20,542 ⇒ 21\n\t\t\t\t\n\t\t\t\t\n\t\t\t\tR - Destino\n\t\t\t\t\n\t\t\t\t\tCUSTO 150 de Mana ⇒ 100 de Mana\n\t\t\t\t\n\t\t\t\n\t\t\n\t\n\t\n\t\t\n\t\t\t\n\t\t\t\t\n\t\t\t\tUdyr\n\t\t\t\tVida base, Mana e Velocidade de Movimento aumentadas. Regeneração de Mana reduzida.\n\t\t\t\t\n\t\t\t\t\tEsse andarilho espiritual tem trilhado uma jornada solitária e não está se saindo bem em lugar algum. Para alguém que é historicamente um dos Campeões mais rápidos quando o assunto é sair correndo por aí, ele foi deixado bem para trás. Aumentaremos sua VdM base para que ele possa alcançar suas presas e arredondaremos alguns outros atributos.\n\t\t\t\t\n\t\t\t\t\n\t\t\t\tAtributos base\n\t\t\t\t\n\t\t\t\t\tVELOCIDADE DE MOVIMENTO 345 ⇒ 350\n\t\t\t\t\n\t\t\t\t\n\t\t\t\t\tVIDA 593,32 ⇒ 594\n\t\t\t\t\n\t\t\t\t\n\t\t\t\t\tMANA 270,4 ⇒ 271\n\t\t\t\t\n\t\t\t\t\n\t\t\t\t\tREGENERAÇÃO DE MANA 7,506 ⇒ 7,5\n\t\t\t\t\n\t\t\t\n\t\t\n\t\n\n\t\n\t\tBalanceamento no URF\n\t\n\t\n\t\t\n\t\t\t\n\t\t\t\t\n\t\t\t\t\tO URF estará de volta na 10.10, que chegará no dia 14 de maio! O experimento do URF com Seleção no ano passado teve um ótimo resultado, com um envolvimento mais saudável no modo e até em Summoner's Rift posteriormente.  Acreditamos que parte de todo esse sucesso pode ser atribuído ao constante balanceamento específico para o modo. Portanto, temos mais ajustes logo abaixo que manterão suas partidas divertidas e frenéticas.  Bom URF para vocês!\n\t\t\t\t\n\t\t\t\t\n\t\t\t\tFortalecimentos na 10.10\n\t\t\t\t\n\t\t\t\t\tAshe Normal ⇒ +10% de dano causado e -5% de dano sofrido\n\t\t\t\t\n\t\t\t\t\n\t\t\t\t\tCaitlyn Normal ⇒ +5% de dano causado e -5% de dano sofrido\n\t\t\t\t\n\t\t\t\t\n\t\t\t\t\tDiana -5% de dano causado ⇒ Normal\n\t\t\t\t\n\t\t\t\t\n\t\t\t\t\tEzreal Normal ⇒ +5% de dano causado e -5% de dano sofrido\n\t\t\t\t\n\t\t\t\t\n\t\t\t\t\tGangplank Normal ⇒ Geração de Serpentes de Prata 3 vezes maior\n\t\t\t\t\n\t\t\t\t\n\t\t\t\t\tGnar +10% de dano causado e -10% de dano sofrido ⇒ +10% de dano causado e -15% de dano sofrido\n\t\t\t\t\n\t\t\t\t\n\t\t\t\t\tJanna -8% de escudo ⇒ Normal\n\t\t\t\t\n\t\t\t\t\n\t\t\t\t\tJayce -5% de dano causado ⇒ Normal\n\t\t\t\t\n\t\t\t\t\n\t\t\t\t\tJinx Normal ⇒ +5% de dano causado e -5% de dano sofrido\n\t\t\t\t\n\t\t\t\t\n\t\t\t\t\tKarthus -15% de dano causado ⇒ -10% de dano causado\n\t\t\t\t\n\t\t\t\t\n\t\t\t\t\tLucian Normal ⇒ +5% de dano causado e -5% de dano sofrido\n\t\t\t\t\n\t\t\t\t\n\t\t\t\t\tMiss Fortune Normal ⇒ +5% de dano causado e -5% de dano sofrido\n\t\t\t\t\n\t\t\t\t\n\t\t\t\t\tNidalee -5% de dano sofrido ⇒ +10% de dano causado e -10% de dano sofrido\n\t\t\t\t\n\t\t\t\t\n\t\t\t\t\tOlaf Normal ⇒ -5% de dano sofrido\n\t\t\t\t\n\t\t\t\t\n\t\t\t\t\tPyke -5% de dano sofrido e -5% de cura ⇒ +5% de dano causado e -10% de dano sofrido\n\t\t\t\t\n\t\t\t\t\n\t\t\t\t\tRakan -10% de escudo ⇒ Normal\n\t\t\t\t\n\t\t\t\t\n\t\t\t\t\tRyze +2% de dano causado e -10% de dano sofrido ⇒ +5% de dano causado e -10% de dano sofrido\n\t\t\t\t\n\t\t\t\t\n\t\t\t\t\tSenna Normal ⇒ +10% de dano causado e -5% de dano sofrido\n\t\t\t\t\n\t\t\t\t\n\t\t\t\t\tSett -5% de dano sofrido ⇒ +10% de dano causado e -10% de dano sofrido\n\t\t\t\t\n\t\t\t\t\n\t\t\t\t\tSONA -5% de dano causado, -5% de cura e -5% de escudo ⇒ -5% de cura e -5% de escudo\n\t\t\t\t\n\t\t\t\t\n\t\t\t\t\tTalon -5% de dano causado ⇒ Normal\n\t\t\t\t\n\t\t\t\t\n\t\t\t\t\tVel'Koz -5% de dano causado ⇒ Normal\n\t\t\t\t\n\t\t\t\t\n\t\t\t\t\tVi -5% de dano causado ⇒ Normal\n\t\t\t\t\n\t\t\t\t\n\t\t\t\t\tXayah -12% de dano causado ⇒ -10% de dano causado\n\t\t\t\t\n\t\t\t\t\n\t\t\t\tEnfraquecimentos na 10.10\n\t\t\t\t\n\t\t\t\t\tAlistar +5% de dano causado e -10% de dano sofrido ⇒ +5% de dano causado e -5% de dano sofrido\n\t\t\t\t\n\t\t\t\t\n\t\t\t\t\tAnnie Normal ⇒ -5% de dano causado\n\t\t\t\t\n\t\t\t\t\n\t\t\t\t\tCorki +10% de dano causado ⇒ Normal\n\t\t\t\t\n\t\t\t\t\n\t\t\t\t\tElise +10% de dano causado e -10% de dano sofrido ⇒ +5% de dano causado e -10% de dano sofrido\n\t\t\t\t\n\t\t\t\t\n\t\t\t\t\tEvelynn +20% de dano causado ⇒ +10% de dano causado e -5% de dano sofrido\n\t\t\t\t\n\t\t\t\t\n\t\t\t\t\tIllaoi +5% de dano causado e -15% de dano sofrido ⇒ +5% de dano causado e -10% de dano sofrido\n\t\t\t\t\n\t\t\t\t\n\t\t\t\t\tIvern -10% de dano sofrido ⇒ -5% de dano sofrido\n\t\t\t\t\n\t\t\t\t\n\t\t\t\t\tJax -5% de dano causado ⇒ -5% de dano causado e +5% de dano sofrido\n\t\t\t\t\n\t\t\t\t\n\t\t\t\t\tKatarina +10% de dano causado e -5% de dano sofrido ⇒ +5% de dano causado e -5% de dano sofrido\n\t\t\t\t\n\t\t\t\t\n\t\t\t\t\tLeona -3% de dano causado e -10% de dano sofrido ⇒ Normal\n\t\t\t\t\n\t\t\t\t\n\t\t\t\t\tMaokai -5% de dano sofrido e -10% de cura ⇒ -5% de dano causado, +5% de dano sofrido e -10% de cura\n\t\t\t\t\n\t\t\t\t\n\t\t\t\t\tNami -10% de cura ⇒ +5% de dano sofrido e -10% de cura\n\t\t\t\t\n\t\t\t\t\n\t\t\t\t\tOrnn +10% de dano causado e -25% de dano sofrido ⇒ +15% de dano causado e -15% de dano sofrido\n\t\t\t\t\n\t\t\t\t\n\t\t\t\t\tPoppy -5% de dano sofrido ⇒ Normal\n\t\t\t\t\n\t\t\t\t\n\t\t\t\t\tQuinn +15% de dano causado ⇒ +5% de dano causado e -5% de dano sofrido\n\t\t\t\t\n\t\t\t\t\n\t\t\t\t\tRammus +15% de dano causado e -12% de dano sofrido ⇒ +10% de dano causado e -12% de dano sofrido\n\t\t\t\t\n\t\t\t\t\n\t\t\t\t\tRek'Sai +5% de dano causado e -20% de dano sofrido ⇒ +10% de dano causado e -10% de dano sofrido\n\t\t\t\t\n\t\t\t\t\n\t\t\t\t\tSejuani -10% de dano sofrido ⇒ -5% de dano sofrido\n\t\t\t\t\n\t\t\t\t\n\t\t\t\t\tShaco -12% de dano causado ⇒ -12% de dano causado e +10% de dano sofrido\n\t\t\t\t\n\t\t\t\t\n\t\t\t\t\tSion +10% de dano causado e -15% de dano sofrido ⇒ +10% de dano causado e -10% de dano sofrido\n\t\t\t\t\n\t\t\t\t\n\t\t\t\t\tSkarner Normal ⇒ -5% de dano causado\n\t\t\t\t\n\t\t\t\t\n\t\t\t\t\tSylas -5% de dano sofrido ⇒ Normal\n\t\t\t\t\n\t\t\t\t\n\t\t\t\t\tUdyr +10% de dano causado e -15% de dano sofrido ⇒ +10% de dano causado e -10% de dano sofrido\n\t\t\t\t\n\t\t\t\t\n\t\t\t\t\tUrgot +15% de dano causado e -10% de dano sofrido ⇒ +10% de dano causado e -10% de dano sofrido\n\t\t\t\t\n\t\t\t\t\n\t\t\t\t\tVladimir -8% de dano sofrido e -5% de cura ⇒ -8% de dano causado, +8% de dano sofrido e -5% de cura\n\t\t\t\t\n\t\t\t\t\n\t\t\t\t\tVolibear Normal ⇒ -5% de dano causado e +5% de dano sofrido\n\t\t\t\t\n\t\t\t\t\n\t\t\t\t\tWukong -5% de dano causado ⇒ -5% de dano causado e +5% de dano sofrido\n\t\t\t\t\n\t\t\t\t\n\t\t\t\t\tYorick -10% de dano sofrido ⇒ -5% de dano sofrido\n\t\t\t\t\n\t\t\t\t\n\t\t\t\t\tYuumi -10% de dano sofrido e -25% de cura ⇒ -20% de dano causado e -30% de cura\n\t\t\t\t\n\t\t\t\t\n\t\t\t\t\tZac -15% de dano sofrido ⇒ -5% de dano sofrido\n\t\t\t\t\n\t\t\t\n\t\t\n\t\n\n\t\n\t\tCorreção de bugs e mudanças de qualidade de vida\n\t\n\t\n\t\t\n\t\t\t\n\t\t\t\t\n\t\t\t\t\tOs efeitos visuais e sonoros da passiva do W - Escudo de Durand do Galio foram atualizados.\n\t\t\t\t\tPenalidades por abandono agora contarão o tempo de penalidade correto entre abandonos (o temporizador da punição agora será devidamente redefinido depois de 23 horas).\n\t\t\t\t\tAs sombras do W - Sombra Viva e R - Marca Fatal do Zed deixam de ficar sobrepostas ao serem conjuradas rapidamente no mesmo alvo.\n\t\t\t\t\tSett agora termina de conjurar seu R - Hora do Show em clones de Campeões mesmo quando eles estiverem quase expirando.\n\t\t\t\t\tSoraka não pode mais silenciar permanentemente um Campeão inimigo com o E - Equinócio até que ele morra e ressurja.\n\t\t\t\t\tLissandra agora cria corretamente um Servo Congelado do Master Yi quando ele é abatido durante o Q - Ataque Alpha.\n\t\t\t\t\tKalista não pode mais realizar ataques básicos enquanto canaliza o feitiço Teleporte ao inserir comandos de ataque repetidamente.\n\t\t\t\t\tFiddlesticks não consegue mais andar enquanto canaliza W - Colheita Farta se seu alvo entra em um estado inalvejável.\n\t\t\t\t\tElise agora consegue conjurar o E - Rapel corretamente em alvos como sentinelas, Pinstouros, Florividentes etc.\n\t\t\t\t\tConjurar o W - Guerreiro Trapaceiro do Wukong enquanto o Campeão inimigo está preparando um ataque básico fortalecido deixa de fazer com que ele perca o controle do personagem.\n\t\t\t\t\tO clone do R - Alucinação do Shaco agora causa corretamente 60% de dano proveniente de itens com efeitos ao contato.\n\t\t\t\t\n\t\t\t\n\t\t\n\t\n\n\t\n\t\tCromas e skins futuros\n\t\n\t\n\t\t\n\t\t\t\n\t\t\t\tAs skins abaixo serão lançadas nesta atualização. Baixe o aplicativo League Displays para conferir ilustrações em alta resolução!\n\t\n\t\t\t\t\t\n\t\t\t\t\t\t\n\t\t\t\t\t\tPulsefire Lucian\n\t\t\t\t\t\n\t\t\t\t\t\n\t\t\t\t\t\t\n\t\t\t\t\t\tPulsefire Lucian Edição de Prestígio\n\t\t\t\t\t\n\t\t\t\t\n\t\t\t\t\n\t\t\t\t\t\n\t\t\t\t\t\t\n\t\t\t\t\t\tPulsefire Pantheon\n\t\t\t\t\t\n\t\t\t\t\t\n\t\t\t\t\t\t\n\t\t\t\t\t\tPulsefire Fiora\n\t\t\t\t\t\n\t\t\t\t\n\t\t\t\t\n\t\t\t\t\t\n\t\t\t\t\t\t\n\t\t\t\t\t\tPulsefire Ekko\n\t\t\t\t\t\n\t\t\t\t\t\n\t\t\t\t\t\n\t\t\t\t\t\t\n\t\t\t\t\t\tPulsefire Lucian\n\t\t\t\t\t\n\t\t\t\t\t\n\t\t\t\t\t\t\n\t\t\t\t\t\tPulsefire Lucian Edição de Prestígio\n\t\t\t\t\t\n\t\t\t\t\n\t\t\t\t\n\t\t\t\t\t\n\t\t\t\t\t\t\n\t\t\t\t\t\tPulsefire Pantheon\n\t\t\t\t\t\n\t\t\t\t\t\n\t\t\t\t\t\t\n\t\t\t\t\t\tPulsefire Fiora\n\t\t\t\t\t\n\t\t\t\t\n\t\t\t\t\n\t\t\t\t\t\n\t\t\t\t\t\t\n\t\t\t\t\t\tPulsefire Ekko\n\t\t\t\t\t\n\t\t\t\t\n\t\t\t\n\t\t\n\t\n\t\n\t\t\n\t\t\t\n\t\t\t\tOs cromas abaixo serão lançados nesta atualização:\n\n\t\t\t\t\t\n\t\t\t\t\t\t\n\t\t\t\t\t\tPulsefire Caitlyn\n\t\t\t\t\t\n\t\t\t\t\t\n\t\t\t\t\t\t\n\t\t\t\t\t\tPulsefire Twisted Fate\n\t\t\t\t\t\n\t\t\t\t\n\t\t\t\t\n\t\t\t\t\t\n\t\t\t\t\t\t\n\t\t\t\t\t\tPulsefire Riven\n\t\t\t\t\t\n\t\t\t\t\t\n\t\t\t\t\t\t\n\t\t\t\t\t\tPulsefire Shen\n\t\t\t\t\t\n\t\t\t\t\n\t\t\t\t\n\t\t\t\t\t\n\t\t\t\t\t\t\n\t\t\t\t\t\tPulsefire Pantheon\n\t\t\t\t\t\n\t\t\t\t\t\n\t\t\t\t\t\t\n\t\t\t\t\t\tPulsefire Fiora\n\t\t\t\t\t\n\t\t\t\t\n\t\t\t\t\n\t\t\t\t\t\n\t\t\t\t\t\t\n\t\t\t\t\t\tPulsefire Ekko"
 },
 "champs": [
  {
   "campeao": "Annie",
   "img": "Annie.png",
   "mod": "Redução de dano do E aumentada e aura de queima do Tibbers fortalecida.",
   "nota": "Fortaleceremos o Tibbers para encorajar quem joga de Annie a brincar mais com ele (e nunca com fósforos). Também aumentaremos a redução de dano do Escudo Fundido, já que a habilidade estava um pouco fraca desde sua pequena atualização na 9.18.",
   "habilidades": [
    {
     "nome": "E - Escudo Fundido",
     "atributos": [
      {
       "atributo": "REDUÇÃO DE DANO",
       "antes": "10/13/16/19/22%",
       "depois": "13/17/21/25/29%"
      }
     ],
     "img": "AnnieE.png"
    },
    {
     "nome": "R - Invocar: Tibbers",
     "atributos": [
      {
       "atributo": "DANO DA AURA DO TIBBERS",
       "antes": "10/15/20 (+0,1 de Poder de Habilidade)",
       "depois": "20/30/40 (+0,12 de Poder de Habilidade)"
      }
     ],
     "img": "AnnieR.png"
    }
   ]
  },
  {
   "campeao": "Diana",
   "img": "Diana.png",
   "mod": "Vida base e Dano de Ataque reduzidos.",
   "nota": "Diana está se mostrando o terror das partidas de alto e médio nível de habilidade e, Apesar de sua agressividade na rota ser algo planejado, achamos que ela não está pagando o preço certo por se colocar em risco.",
   "habilidades": [
    {
     "nome": "Atributos base",
     "atributos": [
      {
       "atributo": "VIDA",
       "antes": "594",
       "depois": "570"
      },
      {
       "atributo": "DANO DE ATAQUE",
       "antes": "57,04",
       "depois": "57"
      }
     ]
    }
   ]
  },
  {
   "campeao": "Irelia",
   "img": "Irelia.png",
   "mod": "Dano base do E aumentado.",
   "nota": "Irelia permaneceu enfraquecida em todos os níveis de jogo por conta do cenário profissional, mas finalmente deixou de dominar as escolhas. Isso pede um empurrãozinho na direção certa.",
   "habilidades": [
    {
     "nome": "E - Dueto Impecável",
     "atributos": [
      {
       "atributo": "DANO BASE",
       "antes": "70/110/150/190/230",
       "depois": "80/125/170/215/260"
      }
     ],
     "img": "IreliaE.png"
    }
   ]
  },
  {
   "campeao": "Katarina",
   "img": "Katarina.png",
   "mod": "Multiplicador de PdH das adagas da Passiva reduzido.",
   "nota": "Por outro lado, essa outra fanática por lâminas anda aparecendo consistentemente no limite do balanceamento e, portanto, reduziremos os multiplicadores de PdH. Adagas mais afiadas serão necessárias se ela quiser continuar explodindo os inimigos por aí.",
   "habilidades": [
    {
     "nome": "Passiva - Voracidade",
     "atributos": [
      {
       "atributo": "MULTIPLICADOR DE DANO DA ADAGA",
       "antes": "0,55/0,70/0,85/1,0 de Poder de Habilidade",
       "depois": "0,55/0,66/0,77/0,88 de Poder de Habilidade"
      }
     ],
     "img": "Katarina_Passive.png"
    }
   ]
  },
  {
   "campeao": "Kayn",
   "img": "Kayn.png",
   "mod": "Cura da Passiva do Rhaast reduzida.",
   "nota": "Embora o Assassino das Sombras pareça estar no lugar certo, o Darkin anda atravessando demais os ̶i̶n̶i̶m̶i̶g̶o̶s̶ limites. Isso pede um enfraquecimento específico na utilidade da forma.",
   "habilidades": [
    {
     "nome": "Passiva - A Foice Darkin",
     "atributos": [
      {
       "atributo": "CURA DO RHAAST",
       "antes": "34,5% - 43% do dano causado (níveis 1 a 18)",
       "depois": "30% - 40% do dano causado (níveis 1 a 18)"
      }
     ],
     "img": "Kayn_Passive_Primary.png"
    }
   ]
  },
  {
   "campeao": "Kled",
   "img": "Kled.png",
   "mod": "Tempo de Recarga do Q aumentado.",
   "nota": "Aumentar o Tempo de Recarga significa que esse corajoso yordle e sua não-tão-corajosa montaria precisarão pensar duas vezes antes de tentar pescar alguém nos primeiros níveis.",
   "habilidades": [
    {
     "nome": "Q - Armadilha na Corda",
     "atributos": [
      {
       "atributo": "TEMPO DE RECARGA",
       "antes": "9/8,5/8/7,5/7s",
       "depois": "11/10/9/8/7s"
      }
     ],
     "img": "KledQ.png"
    }
   ]
  },
  {
   "campeao": "Miss Fortune",
   "img": "MissFortune.png",
   "mod": "Velocidade de Movimento adicional máxima do W reduzida.",
   "nota": "Faremos essa pirata poderosa pisar menos... ̶L̶I̶T̶E̶R̶A̶L̶M̶E̶N̶T̶E̶!",
   "habilidades": [
    {
     "nome": "W - Desfilando",
     "atributos": [
      {
       "atributo": "VELOCIDADE DE MOVIMENTO ADICIONAL MÁXIMA",
       "antes": "60/70/80/90/100",
       "depois": "50/60/70/80/90"
      }
     ],
     "img": "MissFortuneViciousStrikes.png"
    }
   ]
  },
  {
   "campeao": "Maokai",
   "img": "Maokai.png",
   "mod": "Mana base reduzida. Custo do Q aumentado.",
   "nota": "Maokai anda no topo da rota superior! Daremos a ele um pequeno enfraquecimento na esperança de cortar o mal pela raiz. (ba dum, tss)",
   "habilidades": [
    {
     "nome": "Atributos base",
     "atributos": [
      {
       "atributo": "MANA",
       "antes": "377,28",
       "depois": "375"
      }
     ]
    },
    {
     "nome": "Q - Esmagamento Espinhoso",
     "atributos": [
      {
       "atributo": "CUSTO",
       "antes": "50 de Mana",
       "depois": "60 de Mana"
      }
     ],
     "img": "MaokaiQ.png"
    }
   ]
  },
  {
   "campeao": "Nidalee",
   "img": "Nidalee.png",
   "mod": "Multiplicador de dano do Q aumentado.",
   "nota": "Tentaremos colocar a Nida de volta na caçada fortalecendo sua habilidade mais famosa conforme ela escala para o fim de jogo.",
   "habilidades": [
    {
     "nome": "Q - Arremessar Lança",
     "atributos": [
      {
       "atributo": "MULTIPLICADOR DE DANO",
       "antes": "0,4 de Poder de Habilidade (máximo de 1,2 de Poder de Habilidade)",
       "depois": "0,5 de Poder de Habilidade (máximo de 1,5 de Poder de Habilidade)"
      }
     ],
     "img": "JavelinToss.png"
    }
   ]
  },
  {
   "campeao": "Sivir",
   "img": "Sivir.png",
   "mod": "Restauração de Mana do E aumentada.",
   "nota": "Fortaleceremos o restauração de Mana para encorajar os jogadores de Sivir a dominar a arte de mandar os inimigos \"pra trás\" ou elogiar uma \"bela tentativa\".",
   "habilidades": [
    {
     "nome": "E - Escudo de Feitiço",
     "atributos": [
      {
       "atributo": "RESTAURAÇÃO DE MANA",
       "antes": "80/95/110/125/140",
       "depois": "110/120/130/140/150"
      }
     ],
     "img": "SivirE.png"
    }
   ]
  },
  {
   "campeao": "Soraka",
   "img": "Soraka.png",
   "mod": "Dano base do Q aumentado. Redução do custo de Vida do W aumentado.",
   "nota": "Segundo nosso setor de astrologia, as próximas duas semanas serão mais complicadas para os inimigos da Sorakinha.",
   "habilidades": [
    {
     "nome": "Q - Chamado Estelar",
     "atributos": [
      {
       "atributo": "DANO BASE",
       "antes": "75/110/145/180/215",
       "depois": "85/120/155/190/225"
      }
     ],
     "img": "SorakaQ.png"
    },
    {
     "nome": "W - Infusão Astral",
     "atributos": [
      {
       "atributo": "REDUÇÃO DO CUSTO DE VIDA",
       "antes": "60/70/80/90/100%",
       "depois": "80/85/90/95/100%"
      }
     ],
     "img": "SorakaW.png"
    }
   ]
  },
  {
   "campeao": "Taric",
   "img": "Taric.png",
   "mod": "Crescimento de Vida base reduzido. Multiplicador de Armadura adicional do W reduzido nos últimos níveis.",
   "nota": "Faremos com que a sobrevivência de Taric dependa mais do uso de habilidades e reduziremos os atributos defensivos brutos dele e de seu aliado conectado.",
   "habilidades": [
    {
     "nome": "Atributos base",
     "atributos": [
      {
       "atributo": "CRESCIMENTO DE VIDA",
       "antes": "90",
       "depois": "85"
      }
     ]
    },
    {
     "nome": "W - Bastião",
     "atributos": [
      {
       "atributo": "ADICIONAL ARMADURA",
       "antes": "10/12,5/15/17,5/20% da Armadura de Taric",
       "depois": "10/11/12/13/14% da Armadura de Taric"
      }
     ],
     "img": "TaricW.png"
    }
   ]
  },
  {
   "campeao": "Twisted Fate",
   "img": "TwistedFate.png",
   "mod": "Dano de Ataque base e Armadura aumentados. Custo de Mana do R reduzido.",
   "nota": "Nosso TF anda sem sorte nas cartas e está bem sumido, apesar de ter conseguido escapar daquela bruxa do mar. Vamos ajudá-lo reduzindo um pouco o custo da ult, deixando-a mais alinhada com seus oponentes. Também daremos uma alavancada em seus atributos base para aumentar a capacidade de coleta e presença no início de jogo.",
   "habilidades": [
    {
     "nome": "Atributos base",
     "atributos": [
      {
       "atributo": "DANO DE ATAQUE",
       "antes": "49,954",
       "depois": "52"
      },
      {
       "atributo": "ARMADURA",
       "antes": "20,542",
       "depois": "21"
      }
     ]
    },
    {
     "nome": "R - Destino",
     "atributos": [
      {
       "atributo": "CUSTO",
       "antes": "150 de Mana",
       "depois": "100 de Mana"
      }
     ],
     "img": "Destiny.png"
    }
   ]
  },
  {
   "campeao": "Udyr",
   "img": "Udyr.png",
   "mod": "Vida base, Mana e Velocidade de Movimento aumentadas. Regeneração de Mana reduzida.",
   "nota": "Esse andarilho espiritual tem trilhado uma jornada solitária e não está se saindo bem em lugar algum. Para alguém que é historicamente um dos Campeões mais rápidos quando o assunto é sair correndo por aí, ele foi deixado bem para trás. Aumentaremos sua VdM base para que ele possa alcançar suas presas e arredondaremos alguns outros atributos.",
   "habilidades": [
    {
     "nome": "Atributos base",
     "atributos": [
      {
       "atributo": "VELOCIDADE DE MOVIMENTO",
       "antes": "345",
       "depois": "350"
      },
      {
       "atributo": "VIDA",
       "antes": "593,32",
       "depois": "594"
      },
      {
       "atributo": "MANA",
       "antes": "270,4",
       "depois": "271"
      },
      {
       "atributo": "REGENERAÇÃO DE MANA",
       "antes": "7,506",
       "depois": "7,5"
      }
     ]
    }
   ]
  }
 ],
 "runes": [],
 "fixes": [
  {
   "note": "Os efeitos visuais e sonoros da passiva do W - Escudo de Durand do Galio foram atualizados."
  },
  {
   "note": "Penalidades por abandono agora contarão o tempo de penalidade correto entre abandonos (o temporizador da punição agora será devidamente redefinido depois de 23 horas)."
  },
  {
   "note": "As sombras do W - Sombra Viva e R - Marca Fatal do Zed deixam de ficar sobrepostas ao serem conjuradas rapidamente no mesmo alvo."
  },
  {
   "note": "Sett agora termina de conjurar seu R - Hora do Show em clones de Campeões mesmo quando eles estiverem quase expirando."
  },
  {
   "note": "Soraka não pode mais silenciar permanentemente um Campeão inimigo com o E - Equinócio até que ele morra e ressurja.",
   "champs": [
    "Soraka"
   ]
  },
  {
   "note": "Lissandra agora cria corretamente um Servo Congelado do Master Yi quando ele é abatido durante o Q - Ataque Alpha."
  },
  {
   "note": "Kalista não pode mais realizar ataques básicos enquanto canaliza o feitiço Teleporte ao inserir comandos de ataque repetidamente."
  },
  {
   "note": "Fiddlesticks não consegue mais andar enquanto canaliza W - Colheita Farta se seu alvo entra em um estado inalvejável."
  },
  {
   "note": "Elise agora consegue conjurar o E - Rapel corretamente em alvos como sentinelas, Pinstouros, Florividentes etc."
  },
  {
   "note": "Conjurar o W - Guerreiro Trapaceiro do Wukong enquanto o Campeão inimigo está preparando um ataque básico fortalecido deixa de fazer com que ele perca o controle do personagem."
  },
  {
   "note": "O clone do R - Alucinação do Shaco agora causa corretamente 60% de dano proveniente de itens com efeitos ao contato."
  }
 ]
}